MANIFEST.in
NEWS.txt
README.rst
setup.py
src/StreamSampler.egg-info/SOURCES.txt
src/streamsampler/__init__.py
src/streamsampler/cli.py
src/streamsampler/streamsampler.py
src/streamsampler.egg-info/PKG-INFO
src/streamsampler.egg-info/SOURCES.txt
src/streamsampler.egg-info/dependency_links.txt
src/streamsampler.egg-info/entry_points.txt
src/streamsampler.egg-info/not-zip-safe
src/streamsampler.egg-info/top_level.txt