Metadata-Version: 1.1
Name: StreamSampler
Version: 0.1.0
Summary: Data sampler from streaming data
Home-page: https://github.com/keisukefukuda/streamsampler
Author: Keisuke Fukuda
Author-email: keisukefukuda@gmail.com
License: MIT License
Keywords: Reservior sampling,
Platform: UNKNOWN
Classifier: Development Status :: 4 - Beta
Classifier: License :: OSI Approved :: MIT License
Classifier: Programming Language :: Python
Classifier: Programming Language :: Python :: 2
Classifier: Topic :: Text Processing :: Filters
